pylastic_exporter/__init__.py
pylastic_exporter/__main__.py
pylastic_exporter/main.py
pylastic_exporter-2.0.15.dist-info/LICENSE.txt
pylastic_exporter-2.0.15.dist-info/METADATA
pylastic_exporter-2.0.15.dist-info/WHEEL
pylastic_exporter-2.0.15.dist-info/entry_points.txt
pylastic_exporter-2.0.15.dist-info/top_level.txt
pylastic_exporter-2.0.15.dist-info/RECORD
