Metadata-Version: 2.1
Name: pylastic-exporter
Version: 2.0.15
Summary: Create CSV from elasticsearch
Home-page: https://github.com/alexperezortuno/elastic-export
Author: Alex Pérez Ortuño
Author-email: alexperezortuno@gmail.com
License: LICENSE
Requires-Python: >=3.8
License-File: LICENSE.txt
Requires-Dist: numpy (==1.22.3)
Requires-Dist: pandas (==1.4.2)
Requires-Dist: elastic-transport (==8.1.0)
Requires-Dist: elasticsearch (==7.17.0)
Requires-Dist: elasticsearch-dsl (==7.4.0)
Requires-Dist: coloredlogs (==15.0.1)
Requires-Dist: python-dotenv (==0.20.0)
